<?xml version="1.0" encoding="UTF-8" standalone="yes"?>
<rtc:RtcProfile rtc:version="0.2" rtc:id="RTC:MasutaniLab:PointCloud:PCToColorCylinder:1.0.0" xmlns:rtc="http://www.openrtp.org/namespaces/rtc" xmlns:rtcExt="http://www.openrtp.org/namespaces/rtc_ext" xmlns:rtcDoc="http://www.openrtp.org/namespaces/rtc_doc" xmlns:xsi="http://www.w3.org/2001/XMLSchema-instance">
    <rtc:BasicInfo xsi:type="rtcExt:basic_info_ext" rtcExt:saveProject="PCToColorCylinder" rtc:updateDate="2019-09-02T14:38:25+09:00" rtc:creationDate="2019-09-02T14:38:25+09:00" rtc:version="1.0.0" rtc:vendor="MasutaniLab" rtc:maxInstances="1" rtc:executionType="PeriodicExecutionContext" rtc:executionRate="1000.0" rtc:description="Extract cylinders from point cloud with color" rtc:category="PointCloud" rtc:componentKind="DataFlowComponent" rtc:activityType="PERIODIC" rtc:componentType="STATIC" rtc:name="PCToColorCylinder">
        <rtcExt:VersionUpLogs></rtcExt:VersionUpLogs>
        <rtcExt:VersionUpLogs></rtcExt:VersionUpLogs>
        <rtcExt:VersionUpLogs></rtcExt:VersionUpLogs>
    </rtc:BasicInfo>
    <rtc:Actions>
        <rtc:OnInitialize xsi:type="rtcDoc:action_status_doc" rtc:implemented="true"/>
        <rtc:OnFinalize xsi:type="rtcDoc:action_status_doc" rtc:implemented="false"/>
        <rtc:OnStartup xsi:type="rtcDoc:action_status_doc" rtc:implemented="false"/>
        <rtc:OnShutdown xsi:type="rtcDoc:action_status_doc" rtc:implemented="false"/>
        <rtc:OnActivated xsi:type="rtcDoc:action_status_doc" rtc:implemented="true"/>
        <rtc:OnDeactivated xsi:type="rtcDoc:action_status_doc" rtc:implemented="true"/>
        <rtc:OnAborting xsi:type="rtcDoc:action_status_doc" rtc:implemented="false"/>
        <rtc:OnError xsi:type="rtcDoc:action_status_doc" rtc:implemented="false"/>
        <rtc:OnReset xsi:type="rtcDoc:action_status_doc" rtc:implemented="false"/>
        <rtc:OnExecute xsi:type="rtcDoc:action_status_doc" rtc:implemented="true"/>
        <rtc:OnStateUpdate xsi:type="rtcDoc:action_status_doc" rtc:implemented="false"/>
        <rtc:OnRateChanged xsi:type="rtcDoc:action_status_doc" rtc:implemented="false"/>
        <rtc:OnAction xsi:type="rtcDoc:action_status_doc" rtc:implemented="false"/>
        <rtc:OnModeChanged xsi:type="rtcDoc:action_status_doc" rtc:implemented="false"/>
    </rtc:Actions>
    <rtc:ConfigurationSet>
        <rtc:Configuration xsi:type="rtcExt:configuration_ext" rtcExt:variableName="" rtc:unit="" rtc:defaultValue="-0.5" rtc:type="float" rtc:name="filterXMin">
            <rtcExt:Properties rtcExt:value="text" rtcExt:name="__widget__"/>
        </rtc:Configuration>
        <rtc:Configuration xsi:type="rtcExt:configuration_ext" rtcExt:variableName="" rtc:unit="" rtc:defaultValue="+0.5" rtc:type="float" rtc:name="filterXMax">
            <rtcExt:Properties rtcExt:value="text" rtcExt:name="__widget__"/>
        </rtc:Configuration>
        <rtc:Configuration xsi:type="rtcExt:configuration_ext" rtcExt:variableName="" rtc:unit="" rtc:defaultValue="-1.0" rtc:type="float" rtc:name="filterYMin">
            <rtcExt:Properties rtcExt:value="text" rtcExt:name="__widget__"/>
        </rtc:Configuration>
        <rtc:Configuration xsi:type="rtcExt:configuration_ext" rtcExt:variableName="" rtc:unit="" rtc:defaultValue="+1.0" rtc:type="float" rtc:name="filterYMax">
            <rtcExt:Properties rtcExt:value="text" rtcExt:name="__widget__"/>
        </rtc:Configuration>
        <rtc:Configuration xsi:type="rtcExt:configuration_ext" rtcExt:variableName="" rtc:unit="" rtc:defaultValue="-1.0" rtc:type="float" rtc:name="filterZMin">
            <rtcExt:Properties rtcExt:value="text" rtcExt:name="__widget__"/>
        </rtc:Configuration>
        <rtc:Configuration xsi:type="rtcExt:configuration_ext" rtcExt:variableName="" rtc:unit="" rtc:defaultValue="-0.4" rtc:type="float" rtc:name="filterZMax">
            <rtcExt:Properties rtcExt:value="text" rtcExt:name="__widget__"/>
        </rtc:Configuration>
        <rtc:Configuration xsi:type="rtcExt:configuration_ext" rtcExt:variableName="" rtc:unit="" rtc:defaultValue="0.01" rtc:type="float" rtc:name="leafSize">
            <rtcExt:Properties rtcExt:value="text" rtcExt:name="__widget__"/>
        </rtc:Configuration>
        <rtc:Configuration xsi:type="rtcExt:configuration_ext" rtcExt:variableName="" rtc:unit="" rtc:defaultValue="10" rtc:type="int" rtc:name="findingIterationLimit">
            <rtcExt:Properties rtcExt:value="text" rtcExt:name="__widget__"/>
        </rtc:Configuration>
        <rtc:Configuration xsi:type="rtcExt:configuration_ext" rtcExt:variableName="" rtc:unit="" rtc:defaultValue="1000" rtc:type="int" rtc:name="segmentationMaxIteration">
            <rtcExt:Properties rtcExt:value="text" rtcExt:name="__widget__"/>
        </rtc:Configuration>
        <rtc:Configuration xsi:type="rtcExt:configuration_ext" rtcExt:variableName="" rtc:unit="" rtc:defaultValue="0.05" rtc:type="float" rtc:name="segmentationDistanceThreshold">
            <rtcExt:Properties rtcExt:value="text" rtcExt:name="__widget__"/>
        </rtc:Configuration>
        <rtc:Configuration xsi:type="rtcExt:configuration_ext" rtcExt:variableName="" rtc:unit="" rtc:defaultValue="0.01" rtc:type="float" rtc:name="segmentationRadiusMin">
            <rtcExt:Properties rtcExt:value="text" rtcExt:name="__widget__"/>
        </rtc:Configuration>
        <rtc:Configuration xsi:type="rtcExt:configuration_ext" rtcExt:variableName="" rtc:unit="" rtc:defaultValue="0.05" rtc:type="float" rtc:name="segmentationRadiusMax">
            <rtcExt:Properties rtcExt:value="text" rtcExt:name="__widget__"/>
        </rtc:Configuration>
        <rtc:Configuration xsi:type="rtcExt:configuration_ext" rtcExt:variableName="" rtc:unit="" rtc:defaultValue="100" rtc:type="int" rtc:name="cylinderPointSizeMin">
            <rtcExt:Properties rtcExt:value="text" rtcExt:name="__widget__"/>
        </rtc:Configuration>
        <rtc:Configuration xsi:type="rtcExt:configuration_ext" rtcExt:variableName="" rtc:unit="" rtc:defaultValue="1" rtc:type="int" rtc:name="displayHistogram">
            <rtcExt:Properties rtcExt:value="text" rtcExt:name="__widget__"/>
        </rtc:Configuration>
        <rtc:Configuration xsi:type="rtcExt:configuration_ext" rtcExt:variableName="" rtc:unit="" rtc:defaultValue="16" rtc:type="int" rtc:name="histogramBinNumber">
            <rtcExt:Properties rtcExt:value="text" rtcExt:name="__widget__"/>
        </rtc:Configuration>
        <rtc:Configuration xsi:type="rtcExt:configuration_ext" rtcExt:variableName="" rtc:unit="" rtc:defaultValue="127" rtc:type="int" rtc:name="saturationMin">
            <rtcExt:Properties rtcExt:value="text" rtcExt:name="__widget__"/>
        </rtc:Configuration>
        <rtc:Configuration xsi:type="rtcExt:configuration_ext" rtcExt:variableName="" rtc:unit="" rtc:defaultValue="255" rtc:type="int" rtc:name="saturationMax">
            <rtcExt:Properties rtcExt:value="text" rtcExt:name="__widget__"/>
        </rtc:Configuration>
        <rtc:Configuration xsi:type="rtcExt:configuration_ext" rtcExt:variableName="" rtc:unit="" rtc:defaultValue="0" rtc:type="int" rtc:name="valueMin">
            <rtcExt:Properties rtcExt:value="text" rtcExt:name="__widget__"/>
        </rtc:Configuration>
        <rtc:Configuration xsi:type="rtcExt:configuration_ext" rtcExt:variableName="" rtc:unit="" rtc:defaultValue="255" rtc:type="int" rtc:name="valueMax">
            <rtcExt:Properties rtcExt:value="text" rtcExt:name="__widget__"/>
        </rtc:Configuration>
        <rtc:Configuration xsi:type="rtcExt:configuration_ext" rtcExt:variableName="" rtc:unit="" rtc:defaultValue="0.02" rtc:type="float" rtc:name="sameCylinderCenterDistanceLimit">
            <rtcExt:Properties rtcExt:value="text" rtcExt:name="__widget__"/>
        </rtc:Configuration>
        <rtc:Configuration xsi:type="rtcExt:configuration_ext" rtcExt:variableName="" rtc:unit="" rtc:defaultValue="0.01" rtc:type="float" rtc:name="sameCylinderRadiusDistanceLimit">
            <rtcExt:Properties rtcExt:value="text" rtcExt:name="__widget__"/>
        </rtc:Configuration>
        <rtc:Configuration xsi:type="rtcExt:configuration_ext" rtcExt:variableName="" rtc:unit="" rtc:defaultValue="23" rtc:type="float" rtc:name="sameCylinderHueDistanceLimit">
            <rtcExt:Properties rtcExt:value="text" rtcExt:name="__widget__"/>
        </rtc:Configuration>
        <rtc:Configuration xsi:type="rtcExt:configuration_ext" rtcExt:variableName="" rtc:unit="" rtc:defaultValue="10" rtc:type="int" rtc:name="cylinderAccumulationMin">
            <rtcExt:Properties rtcExt:value="text" rtcExt:name="__widget__"/>
        </rtc:Configuration>
        <rtc:Configuration xsi:type="rtcExt:configuration_ext" rtcExt:variableName="" rtc:unit="" rtc:defaultValue="coordinateTransformation.txt" rtc:type="string" rtc:name="coordinateTransformationFile">
            <rtcExt:Properties rtcExt:value="text" rtcExt:name="__widget__"/>
        </rtc:Configuration>
        <rtc:Configuration xsi:type="rtcExt:configuration_ext" rtcExt:variableName="" rtc:unit="" rtc:defaultValue="0.0" rtc:type="float" rtc:name="calibrationOffsetX">
            <rtcExt:Properties rtcExt:value="text" rtcExt:name="__widget__"/>
        </rtc:Configuration>
        <rtc:Configuration xsi:type="rtcExt:configuration_ext" rtcExt:variableName="" rtc:unit="" rtc:defaultValue="0.0" rtc:type="float" rtc:name="calibrationOffsetY">
            <rtcExt:Properties rtcExt:value="text" rtcExt:name="__widget__"/>
        </rtc:Configuration>
        <rtc:Configuration xsi:type="rtcExt:configuration_ext" rtcExt:variableName="" rtc:unit="" rtc:defaultValue="0.0" rtc:type="float" rtc:name="calibrationOffsetZ">
            <rtcExt:Properties rtcExt:value="text" rtcExt:name="__widget__"/>
        </rtc:Configuration>
    </rtc:ConfigurationSet>
    <rtc:DataPorts xsi:type="rtcExt:dataport_ext" rtcExt:position="LEFT" rtcExt:variableName="" rtc:unit="" rtc:subscriptionType="" rtc:dataflowType="" rtc:interfaceType="" rtc:idlFile="C:\Users\masutani\Documents\MikataArm\PCToColorCylinder\idl\pointcloud.idl" rtc:type="PointCloudTypes::PointCloud" rtc:name="pc" rtc:portType="DataInPort"/>
    <rtc:DataPorts xsi:type="rtcExt:dataport_ext" rtcExt:position="RIGHT" rtcExt:variableName="" rtc:unit="" rtc:subscriptionType="" rtc:dataflowType="" rtc:interfaceType="" rtc:idlFile="C:\Program Files\OpenRTM-aist\1.2.0\rtm\idl\BasicDataType.idl" rtc:type="RTC::TimedDoubleSeq" rtc:name="cylinder" rtc:portType="DataOutPort"/>
    <rtc:Language xsi:type="rtcExt:language_ext" rtc:kind="C++"/>
</rtc:RtcProfile>
